setup.py
django_mailmodel.egg-info/PKG-INFO
django_mailmodel.egg-info/SOURCES.txt
django_mailmodel.egg-info/dependency_links.txt
django_mailmodel.egg-info/requires.txt
django_mailmodel.egg-info/top_level.txt
mailmodel/__init__.py
mailmodel/admin.py
mailmodel/app_settings.py
mailmodel/forms.py
mailmodel/models.py
mailmodel/tests.py
mailmodel/urls.py
mailmodel/views.py
mailmodel/templatetags/__init__.py
mailmodel/templatetags/mailmodel_tags.py