Metadata-Version: 1.0
Name: django-mailmodel
Version: 0.1
Summary: Reusable app for sharing objects by email
Home-page: http://bitbucket.org/surfeurX/django-mailmodel
Author: Amine Chouki
Author-email: surfeurX@gmail.com
License: UNKNOWN
Platform: UNKNOWN
